yi/__init__.py
yi-0.0.6.dist-info/licenses/LICENSE
yi-0.0.6.dist-info/METADATA
yi-0.0.6.dist-info/WHEEL
yi-0.0.6.dist-info/top_level.txt
yi-0.0.6.dist-info/RECORD
