Metadata-Version: 2.4
Name: yi
Version: 0.0.6
Summary: Convert dictionaries to other objects
Home-page: https://github.com/t-c-w/yi
Author: Thor Whalen
License: apache-2.0
Platform: any
License-File: LICENSE
Dynamic: license-file
